FreeradiusXinshourumen/README.md
FreeradiusXinshourumen/__init__.py
FreeradiusXinshourumen/__main__.py
FreeradiusXinshourumen/file.epub
FreeradiusXinshourumen/index.html
FreeradiusXinshourumen/css/__init__.py
FreeradiusXinshourumen/css/annotations.css
FreeradiusXinshourumen/css/main.css
FreeradiusXinshourumen/css/normalize.css
FreeradiusXinshourumen/css/popup.css
FreeradiusXinshourumen/font/__init__.py
FreeradiusXinshourumen/font/fontello.eot
FreeradiusXinshourumen/font/fontello.svg
FreeradiusXinshourumen/font/fontello.ttf
FreeradiusXinshourumen/font/fontello.woff
FreeradiusXinshourumen/img/__init__.py
FreeradiusXinshourumen/img/annotator-glyph-sprite.png
FreeradiusXinshourumen/img/annotator-icon-sprite.png
FreeradiusXinshourumen/img/apple-touch-icon.png
FreeradiusXinshourumen/img/cancelfullscreen.png
FreeradiusXinshourumen/img/close.png
FreeradiusXinshourumen/img/fullscreen.png
FreeradiusXinshourumen/img/loader.gif
FreeradiusXinshourumen/img/menu-icon.png
FreeradiusXinshourumen/img/save.png
FreeradiusXinshourumen/img/saved.png
FreeradiusXinshourumen/img/settings-s.png
FreeradiusXinshourumen/img/settings.png
FreeradiusXinshourumen/img/star.png
FreeradiusXinshourumen/js/__init__.py
FreeradiusXinshourumen/js/epub.js
FreeradiusXinshourumen/js/epub.min.js
FreeradiusXinshourumen/js/epub.min.map
FreeradiusXinshourumen/js/hooks.min.js
FreeradiusXinshourumen/js/hooks.min.map
FreeradiusXinshourumen/js/reader.js
FreeradiusXinshourumen/js/reader.js.map
FreeradiusXinshourumen/js/reader.min.js
FreeradiusXinshourumen/js/reader.min.map
FreeradiusXinshourumen/js/hooks/__init__.py
FreeradiusXinshourumen/js/hooks/extensions/__init__.py
FreeradiusXinshourumen/js/hooks/extensions/highlight.js
FreeradiusXinshourumen/js/libs/__init__.py
FreeradiusXinshourumen/js/libs/jquery.min.js
FreeradiusXinshourumen/js/libs/localforage.min.js
FreeradiusXinshourumen/js/libs/screenfull.js
FreeradiusXinshourumen/js/libs/screenfull.min.js
FreeradiusXinshourumen/js/libs/zip.min.js
freeradius_xinshourumen-2024.3.2.0.dist-info/METADATA
freeradius_xinshourumen-2024.3.2.0.dist-info/WHEEL
freeradius_xinshourumen-2024.3.2.0.dist-info/entry_points.txt
freeradius_xinshourumen-2024.3.2.0.dist-info/top_level.txt
freeradius_xinshourumen-2024.3.2.0.dist-info/RECORD
